<?xml version="1.0" encoding="UTF-8"?><record_update sys_domain="global" table="sn_decision_table_decision_condition">
    <sn_decision_table_decision_condition action="DELETE">
        <decision_input display_value="Affected Documents">339e326c474d9910ab51f109536d4336</decision_input>
        <decision_table display_value="IPE - Celonis - Risk Policy">cbac7e68474d9910ab51f109536d4331</decision_table>
        <default_operator>BETWEEN</default_operator>
        <description/>
        <field/>
        <field_label/>
        <field_parent_table/>
        <label>Affected Docs</label>
        <order>300</order>
        <reference/>
        <sys_class_name>sn_decision_table_decision_condition</sys_class_name>
        <sys_created_by>admin</sys_created_by>
        <sys_created_on>2022-07-29 12:12:39</sys_created_on>
        <sys_domain>global</sys_domain>
        <sys_id>11ff3e68474d9910ab51f109536d433d</sys_id>
        <sys_mod_count>0</sys_mod_count>
        <sys_name/>
        <sys_package display_value="Insight Process Management" source="x_snc_insight_pr_0">39bd5e9747f05510ab51f109536d431c</sys_package>
        <sys_policy/>
        <sys_scope display_value="Insight Process Management">39bd5e9747f05510ab51f109536d431c</sys_scope>
        <sys_update_name>sn_decision_table_decision_condition_11ff3e68474d9910ab51f109536d433d</sys_update_name>
        <sys_updated_by>admin</sys_updated_by>
        <sys_updated_on>2022-07-29 12:12:39</sys_updated_on>
        <type display_value="Integer">aab367c1bf3320001875647fcf073909</type>
    </sn_decision_table_decision_condition>
    <sys_update_version action="INSERT_OR_UPDATE">
        <action>DELETE</action>
        <application display_value="Insight Process Management">39bd5e9747f05510ab51f109536d431c</application>
        <file_path/>
        <instance_id>fcebc747db8eec1049eac597059619dd</instance_id>
        <instance_name>tblevinse2eitomdemo</instance_name>
        <name>sn_decision_table_decision_condition_11ff3e68474d9910ab51f109536d433d</name>
        <payload><![CDATA[<?xml version="1.0" encoding="UTF-8"?><record_update sys_domain="global" table="sn_decision_table_decision_condition"><sn_decision_table_decision_condition action="INSERT_OR_UPDATE"><decision_input display_value="Affected Documents">339e326c474d9910ab51f109536d4336</decision_input><decision_table display_value="IPE - Celonis - Risk Policy">cbac7e68474d9910ab51f109536d4331</decision_table><default_operator>BETWEEN</default_operator><description/><field/><field_label/><field_parent_table/><label>Affected Docs</label><order>300</order><reference/><sys_class_name>sn_decision_table_decision_condition</sys_class_name><sys_created_by>admin</sys_created_by><sys_created_on>2022-07-29 12:12:39</sys_created_on><sys_domain>global</sys_domain><sys_id>11ff3e68474d9910ab51f109536d433d</sys_id><sys_mod_count>0</sys_mod_count><sys_name/><sys_package display_value="Insight Process Management" source="x_snc_insight_pr_0">39bd5e9747f05510ab51f109536d431c</sys_package><sys_policy/><sys_scope display_value="Insight Process Management">39bd5e9747f05510ab51f109536d431c</sys_scope><sys_update_name>sn_decision_table_decision_condition_11ff3e68474d9910ab51f109536d433d</sys_update_name><sys_updated_by>admin</sys_updated_by><sys_updated_on>2022-07-29 12:12:39</sys_updated_on><type display_value="Integer">aab367c1bf3320001875647fcf073909</type></sn_decision_table_decision_condition></record_update>]]></payload>
        <payload_hash>-1574633853</payload_hash>
        <record_name/>
        <reverted_from/>
        <source>b1bd5e9747f05510ab51f109536d431f</source>
        <source_table>sys_update_set</source_table>
        <state>previous</state>
        <sys_created_by>admin</sys_created_by>
        <sys_created_on>2022-07-29 12:12:39</sys_created_on>
        <sys_id>95ffbaac474d9910ab51f109536d4345</sys_id>
        <sys_mod_count>0</sys_mod_count>
        <sys_recorded_at>18249df7b0c0000001</sys_recorded_at>
        <sys_updated_by>admin</sys_updated_by>
        <sys_updated_on>2022-07-29 12:12:39</sys_updated_on>
        <type>Decision Condition</type>
        <update_guid>9dffbaac744d9910a491d28045aaf544</update_guid>
        <update_guid_history>9dffbaac744d9910a491d28045aaf544:-1574633853</update_guid_history>
    </sys_update_version>
    <sys_metadata_delete action="INSERT_OR_UPDATE">
        <sys_audit_delete display_value="">324c83e047cd9910ab51f109536d434a</sys_audit_delete>
        <sys_class_name>sys_metadata_delete</sys_class_name>
        <sys_created_by>admin</sys_created_by>
        <sys_created_on>2022-07-29 13:06:32</sys_created_on>
        <sys_customer_update>false</sys_customer_update>
        <sys_db_object display_value="" name="sn_decision_table_decision_condition">sn_decision_table_decision_condition</sys_db_object>
        <sys_id>0c1555fe61c94b9f91ee3c56cb69e251</sys_id>
        <sys_metadata>11ff3e68474d9910ab51f109536d433d</sys_metadata>
        <sys_mod_count>0</sys_mod_count>
        <sys_name/>
        <sys_package display_value="Insight Process Management" source="x_snc_insight_pr_0">39bd5e9747f05510ab51f109536d431c</sys_package>
        <sys_parent/>
        <sys_policy/>
        <sys_replace_on_upgrade>false</sys_replace_on_upgrade>
        <sys_scope display_value="Insight Process Management">39bd5e9747f05510ab51f109536d431c</sys_scope>
        <sys_scope_delete display_value="">17d7b8e244be45e48a01ac8215c4d439</sys_scope_delete>
        <sys_update_name>sn_decision_table_decision_condition_11ff3e68474d9910ab51f109536d433d</sys_update_name>
        <sys_update_version display_value="sn_decision_table_decision_condition_11ff3e68474d9910ab51f109536d433d">95ffbaac474d9910ab51f109536d4345</sys_update_version>
        <sys_updated_by>admin</sys_updated_by>
        <sys_updated_on>2022-07-29 13:06:32</sys_updated_on>
    </sys_metadata_delete>
</record_update>
