<?xml version="1.0" encoding="UTF-8"?><record_update sys_domain="global" table="sys_declarative_action_assignment">
    <sys_declarative_action_assignment action="DELETE">
        <action/>
        <action_attributes>{"activityView":"stacked","playbookExperienceId":"98e09a560f2200102920c912d4767e1a","parentSysId":"{{sysId}}","parentTable":"{{table}}","compactMode":"false","recordGeneratorQuery":"","isNewParentRecord":"{{isNewRecord}}"}</action_attributes>
        <action_name>Add Playbook</action_name>
        <action_payload/>
        <action_type>type</action_type>
        <active>true</active>
        <button_type>primary</button_type>
        <client_action/>
        <client_conditions/>
        <client_conditions_on_fields/>
        <client_script><![CDATA[function onClick() { }]]></client_script>
        <confirmation_message/>
        <confirmation_required>false</confirmation_required>
        <create_access>false</create_access>
        <declarative_action_render_mode/>
        <declarative_action_type>action_component</declarative_action_type>
        <delete_access>false</delete_access>
        <dependency/>
        <description/>
        <design_icon/>
        <enable_for_all_experiences>false</enable_for_all_experiences>
        <enabled>true</enabled>
        <experience_restricted>false</experience_restricted>
        <field_name/>
        <field_type>glide_date</field_type>
        <form_fields_required>false</form_fields_required>
        <form_position>contexual_sidebar</form_position>
        <group/>
        <group_by>false</group_by>
        <icon/>
        <label>Add Playbook</label>
        <model display_value="Related List">d91731a9534723003eddddeeff7b121c</model>
        <model_conditions/>
        <model_field_required/>
        <order>0</order>
        <payload_map/>
        <read_access>false</read_access>
        <record_conditions/>
        <record_selection_required>false</record_selection_required>
        <required_roles/>
        <requires_value>false</requires_value>
        <script_condition>sn_playbook.PlaybookExperience.parentRecordContainsPlaybook(current)</script_condition>
        <scripted_client_condition/>
        <server_script/>
        <specificity>21</specificity>
        <sys_class_name>sys_declarative_action_assignment</sys_class_name>
        <sys_created_by>TBlev1</sys_created_by>
        <sys_created_on>2023-08-07 10:00:29</sys_created_on>
        <sys_customer_update>false</sys_customer_update>
        <sys_domain>global</sys_domain>
        <sys_id>a353ec4d1be071500f0eda43cc4bcb6b</sys_id>
        <sys_mod_count>2</sys_mod_count>
        <sys_name>Add Playbook</sys_name>
        <sys_overrides/>
        <sys_package display_value="Insight Process Management" source="x_snc_insight_pr_0">39bd5e9747f05510ab51f109536d431c</sys_package>
        <sys_policy/>
        <sys_replace_on_upgrade>false</sys_replace_on_upgrade>
        <sys_scope display_value="Insight Process Management">39bd5e9747f05510ab51f109536d431c</sys_scope>
        <sys_update_name>sys_declarative_action_assignment_a353ec4d1be071500f0eda43cc4bcb6b</sys_update_name>
        <sys_updated_by>TBlev1</sys_updated_by>
        <sys_updated_on>2023-08-07 10:05:49</sys_updated_on>
        <table>x_snc_insight_pr_0_ledger_task</table>
        <tooltip/>
        <ui_component display_value="now-playbook-experience">9d0bc73916d784d8692b89e9553124dc</ui_component>
        <view/>
        <workspace/>
        <write_access>false</write_access>
    </sys_declarative_action_assignment>
    <sys_update_version action="INSERT_OR_UPDATE">
        <action>DELETE</action>
        <application display_value="Insight Process Management">39bd5e9747f05510ab51f109536d431c</application>
        <file_path/>
        <instance_id>532947b4ffaeac889376762fa87efe09</instance_id>
        <instance_name>niketest</instance_name>
        <name>sys_declarative_action_assignment_a353ec4d1be071500f0eda43cc4bcb6b</name>
        <payload>&lt;?xml version="1.0" encoding="UTF-8"?&gt;&lt;record_update sys_domain="global" table="sys_declarative_action_assignment"&gt;&lt;sys_declarative_action_assignment action="INSERT_OR_UPDATE"&gt;&lt;action/&gt;&lt;action_attributes&gt;{"activityView":"stacked","playbookExperienceId":"98e09a560f2200102920c912d4767e1a","parentSysId":"{{sysId}}","parentTable":"{{table}}","compactMode":"false","recordGeneratorQuery":"","isNewParentRecord":"{{isNewRecord}}"}&lt;/action_attributes&gt;&lt;action_name&gt;Add Playbook&lt;/action_name&gt;&lt;action_payload/&gt;&lt;action_type&gt;type&lt;/action_type&gt;&lt;active&gt;true&lt;/active&gt;&lt;button_type&gt;primary&lt;/button_type&gt;&lt;client_action/&gt;&lt;client_conditions/&gt;&lt;client_conditions_on_fields/&gt;&lt;client_script&gt;&lt;![CDATA[function onClick() { }]]&gt;&lt;/client_script&gt;&lt;confirmation_message/&gt;&lt;confirmation_required&gt;false&lt;/confirmation_required&gt;&lt;create_access&gt;false&lt;/create_access&gt;&lt;declarative_action_render_mode/&gt;&lt;declarative_action_type&gt;action_component&lt;/declarative_action_type&gt;&lt;delete_access&gt;false&lt;/delete_access&gt;&lt;dependency/&gt;&lt;description/&gt;&lt;design_icon/&gt;&lt;enable_for_all_experiences&gt;false&lt;/enable_for_all_experiences&gt;&lt;enabled&gt;true&lt;/enabled&gt;&lt;experience_restricted&gt;false&lt;/experience_restricted&gt;&lt;field_name/&gt;&lt;field_type&gt;glide_date&lt;/field_type&gt;&lt;form_fields_required&gt;false&lt;/form_fields_required&gt;&lt;form_position&gt;contexual_sidebar&lt;/form_position&gt;&lt;group/&gt;&lt;group_by&gt;false&lt;/group_by&gt;&lt;icon/&gt;&lt;label&gt;Add Playbook&lt;/label&gt;&lt;model display_value="Related List"&gt;d91731a9534723003eddddeeff7b121c&lt;/model&gt;&lt;model_conditions/&gt;&lt;model_field_required/&gt;&lt;order&gt;0&lt;/order&gt;&lt;payload_map/&gt;&lt;read_access&gt;false&lt;/read_access&gt;&lt;record_conditions/&gt;&lt;record_selection_required&gt;false&lt;/record_selection_required&gt;&lt;required_roles/&gt;&lt;requires_value&gt;false&lt;/requires_value&gt;&lt;script_condition&gt;sn_playbook.PlaybookExperience.parentRecordContainsPlaybook(current)&lt;/script_condition&gt;&lt;scripted_client_condition/&gt;&lt;server_script/&gt;&lt;specificity&gt;21&lt;/specificity&gt;&lt;sys_class_name&gt;sys_declarative_action_assignment&lt;/sys_class_name&gt;&lt;sys_created_by&gt;TBlev1&lt;/sys_created_by&gt;&lt;sys_created_on&gt;2023-08-07 10:00:29&lt;/sys_created_on&gt;&lt;sys_customer_update&gt;false&lt;/sys_customer_update&gt;&lt;sys_domain&gt;global&lt;/sys_domain&gt;&lt;sys_id&gt;a353ec4d1be071500f0eda43cc4bcb6b&lt;/sys_id&gt;&lt;sys_mod_count&gt;2&lt;/sys_mod_count&gt;&lt;sys_name&gt;Add Playbook&lt;/sys_name&gt;&lt;sys_overrides/&gt;&lt;sys_package display_value="Insight Process Management" source="x_snc_insight_pr_0"&gt;39bd5e9747f05510ab51f109536d431c&lt;/sys_package&gt;&lt;sys_policy/&gt;&lt;sys_replace_on_upgrade&gt;false&lt;/sys_replace_on_upgrade&gt;&lt;sys_scope display_value="Insight Process Management"&gt;39bd5e9747f05510ab51f109536d431c&lt;/sys_scope&gt;&lt;sys_update_name&gt;sys_declarative_action_assignment_a353ec4d1be071500f0eda43cc4bcb6b&lt;/sys_update_name&gt;&lt;sys_updated_by&gt;TBlev1&lt;/sys_updated_by&gt;&lt;sys_updated_on&gt;2023-08-07 10:05:49&lt;/sys_updated_on&gt;&lt;table&gt;x_snc_insight_pr_0_ledger_task&lt;/table&gt;&lt;tooltip/&gt;&lt;ui_component display_value="now-playbook-experience"&gt;9d0bc73916d784d8692b89e9553124dc&lt;/ui_component&gt;&lt;view/&gt;&lt;workspace/&gt;&lt;write_access&gt;false&lt;/write_access&gt;&lt;/sys_declarative_action_assignment&gt;&lt;/record_update&gt;</payload>
        <payload_hash>1468064748</payload_hash>
        <record_name>Add Playbook</record_name>
        <reverted_from/>
        <source>d05f909a97afe1d0387553800153afb6</source>
        <source_table>sys_update_set</source_table>
        <state>previous</state>
        <sys_created_by>TBlev1</sys_created_by>
        <sys_created_on>2023-08-07 10:05:49</sys_created_on>
        <sys_id>8a8568cd1b2471500f0eda43cc4bcb06</sys_id>
        <sys_mod_count>0</sys_mod_count>
        <sys_recorded_at>189cf75c63e0000001</sys_recorded_at>
        <sys_updated_by>TBlev1</sys_updated_by>
        <sys_updated_on>2023-08-07 10:05:49</sys_updated_on>
        <type>Action Assignment</type>
        <update_guid>4e8568cdc32471501d53784e22222f05</update_guid>
        <update_guid_history>4e8568cdc32471501d53784e22222f05:1468064748,2c35e44107247150c77b84cc7c25e0f9:897875228,7344a841e124715036a6a56de31acd5c:449069639</update_guid_history>
    </sys_update_version>
    <sys_metadata_delete action="INSERT_OR_UPDATE">
        <sys_audit_delete/>
        <sys_class_name>sys_metadata_delete</sys_class_name>
        <sys_created_by>TBlev1</sys_created_by>
        <sys_created_on>2023-08-07 12:34:06</sys_created_on>
        <sys_customer_update>false</sys_customer_update>
        <sys_db_object display_value="" name="sys_declarative_action_assignment">sys_declarative_action_assignment</sys_db_object>
        <sys_id>3e8f05aceef24750a3dc28c71b8a4490</sys_id>
        <sys_metadata>a353ec4d1be071500f0eda43cc4bcb6b</sys_metadata>
        <sys_mod_count>0</sys_mod_count>
        <sys_name>Add Playbook</sys_name>
        <sys_package display_value="Insight Process Management" source="x_snc_insight_pr_0">39bd5e9747f05510ab51f109536d431c</sys_package>
        <sys_parent/>
        <sys_policy/>
        <sys_replace_on_upgrade>false</sys_replace_on_upgrade>
        <sys_scope display_value="Insight Process Management">39bd5e9747f05510ab51f109536d431c</sys_scope>
        <sys_scope_delete display_value="">17d7b8e244be45e48a01ac8215c4d439</sys_scope_delete>
        <sys_update_name>sys_declarative_action_assignment_a353ec4d1be071500f0eda43cc4bcb6b</sys_update_name>
        <sys_update_version display_value="sys_declarative_action_assignment_a353ec4d1be071500f0eda43cc4bcb6b">8a8568cd1b2471500f0eda43cc4bcb06</sys_update_version>
        <sys_updated_by>TBlev1</sys_updated_by>
        <sys_updated_on>2023-08-07 12:34:06</sys_updated_on>
    </sys_metadata_delete>
</record_update>
