<?xml version="1.0" encoding="UTF-8"?><record_update table="ml_training_request_schedule">
    <ml_training_request_schedule action="INSERT_OR_UPDATE">
        <active>true</active>
        <business_calendar/>
        <capability/>
        <condition/>
        <conditional>false</conditional>
        <entered_time/>
        <max_drift/>
        <ml_capability_definition display_value="">f8d74bdddbc18850a6d183243996194d</ml_capability_definition>
        <ml_solution/>
        <name>Closed alert similarity</name>
        <offset/>
        <offset_type>0</offset_type>
        <run_as display_value="System Administrator">6816f79cc0a8016401c5a33be04be441</run_as>
        <run_as_tz/>
        <run_dayofmonth>1</run_dayofmonth>
        <run_dayofweek/>
        <run_period>1970-01-31 00:00:00</run_period>
        <run_start>2023-03-08 17:24:14</run_start>
        <run_time/>
        <run_type>periodically</run_type>
        <solution_definition/>
        <sys_class_name>ml_training_request_schedule</sys_class_name>
        <sys_created_by>admin</sys_created_by>
        <sys_created_on>2023-03-08 17:24:14</sys_created_on>
        <sys_id>ce381f8887a121108b817b9acebb3527</sys_id>
        <sys_mod_count>0</sys_mod_count>
        <sys_name>Closed alert similarity</sys_name>
        <sys_package display_value="Insight Process Management" source="x_snc_insight_pr_0">39bd5e9747f05510ab51f109536d431c</sys_package>
        <sys_policy/>
        <sys_scope display_value="Insight Process Management">39bd5e9747f05510ab51f109536d431c</sys_scope>
        <sys_update_name>ml_training_request_schedule_ce381f8887a121108b817b9acebb3527</sys_update_name>
        <sys_updated_by>admin</sys_updated_by>
        <sys_updated_on>2023-03-08 17:24:14</sys_updated_on>
        <time_zone/>
        <upgrade_safe>false</upgrade_safe>
    </ml_training_request_schedule>
</record_update>
