<?xml version="1.0" encoding="UTF-8"?><record_update sys_domain="global" table="sn_decision_table_decision_condition">
    <sn_decision_table_decision_condition action="INSERT_OR_UPDATE">
        <decision_input display_value="Output1">464f64cc874dd5108b817b9acebb356a</decision_input>
        <decision_table display_value="IPE - Demand or Case Policy">8f7ee000878dd5108b817b9acebb3555</decision_table>
        <default_operator>STARTSWITH</default_operator>
        <description>Events for Material can be processed via Task Management</description>
        <field/>
        <field_label/>
        <field_parent_table/>
        <label>Is Material</label>
        <order>100</order>
        <reference/>
        <sys_class_name>sn_decision_table_decision_condition</sys_class_name>
        <sys_created_by>admin</sys_created_by>
        <sys_created_on>2022-07-27 12:23:36</sys_created_on>
        <sys_domain>global</sys_domain>
        <sys_id>524f6400878dd5108b817b9acebb3516</sys_id>
        <sys_mod_count>0</sys_mod_count>
        <sys_name/>
        <sys_package display_value="Insight Process Management" source="x_snc_insight_pr_0">39bd5e9747f05510ab51f109536d431c</sys_package>
        <sys_policy/>
        <sys_scope display_value="Insight Process Management">39bd5e9747f05510ab51f109536d431c</sys_scope>
        <sys_update_name>sn_decision_table_decision_condition_524f6400878dd5108b817b9acebb3516</sys_update_name>
        <sys_updated_by>admin</sys_updated_by>
        <sys_updated_on>2022-07-27 12:23:36</sys_updated_on>
        <type display_value="String">747127c1bf3320001875647fcf0739e0</type>
    </sn_decision_table_decision_condition>
</record_update>
